oncall/__init__.py
oncall/app.py
oncall/constants.py
oncall/db.py
oncall/doc_helper.py
oncall/healthcheck.py
oncall/iris.py
oncall/sphinx_extension.py
oncall/utils.py
oncall/api/__init__.py
oncall/api/v0/__init__.py
oncall/api/v0/audit.py
oncall/api/v0/bonus_events.py
oncall/api/v0/event.py
oncall/api/v0/event_link.py
oncall/api/v0/event_override.py
oncall/api/v0/event_swap.py
oncall/api/v0/events.py
oncall/api/v0/events_link.py
oncall/api/v0/ical.py
oncall/api/v0/ical_key.py
oncall/api/v0/ical_key_detail.py
oncall/api/v0/ical_key_requester.py
oncall/api/v0/ical_key_team.py
oncall/api/v0/ical_key_user.py
oncall/api/v0/iris_settings.py
oncall/api/v0/modes.py
oncall/api/v0/notification_types.py
oncall/api/v0/notifications.py
oncall/api/v0/populate.py
oncall/api/v0/preview.py
oncall/api/v0/public_ical.py
oncall/api/v0/role.py
oncall/api/v0/roles.py
oncall/api/v0/roster.py
oncall/api/v0/roster_suggest.py
oncall/api/v0/roster_user.py
oncall/api/v0/roster_users.py
oncall/api/v0/rosters.py
oncall/api/v0/schedule.py
oncall/api/v0/schedules.py
oncall/api/v0/search.py
oncall/api/v0/service.py
oncall/api/v0/service_oncall.py
oncall/api/v0/service_teams.py
oncall/api/v0/services.py
oncall/api/v0/team.py
oncall/api/v0/team_admin.py
oncall/api/v0/team_admins.py
oncall/api/v0/team_changes.py
oncall/api/v0/team_ical.py
oncall/api/v0/team_iris_escalate.py
oncall/api/v0/team_oncall.py
oncall/api/v0/team_service.py
oncall/api/v0/team_services.py
oncall/api/v0/team_subscription.py
oncall/api/v0/team_subscriptions.py
oncall/api/v0/team_summary.py
oncall/api/v0/team_user.py
oncall/api/v0/team_users.py
oncall/api/v0/teams.py
oncall/api/v0/timezones.py
oncall/api/v0/upcoming_shifts.py
oncall/api/v0/user.py
oncall/api/v0/user_ical.py
oncall/api/v0/user_notification.py
oncall/api/v0/user_notifications.py
oncall/api/v0/user_pinned_team.py
oncall/api/v0/user_pinned_teams.py
oncall/api/v0/user_teams.py
oncall/api/v0/users.py
oncall/auth/__init__.py
oncall/auth/login.py
oncall/auth/logout.py
oncall-2.1.7.dist-info/AUTHORS.md
oncall-2.1.7.dist-info/LICENSE
oncall-2.1.7.dist-info/METADATA
oncall-2.1.7.dist-info/NOTICE
oncall-2.1.7.dist-info/WHEEL
oncall-2.1.7.dist-info/entry_points.txt
oncall-2.1.7.dist-info/top_level.txt
oncall-2.1.7.dist-info/RECORD
