Metadata-Version: 2.1
Name: oncall
Version: 2.1.7
Summary: Oncall is a calendar tool designed for scheduling and managing on-call shifts
Home-page: https://github.com/linkedin/oncall
Classifier: Development Status :: 5 - Production/Stable
Classifier: License :: OSI Approved :: BSD License
Classifier: Natural Language :: English
Classifier: Programming Language :: Python :: 3
License-File: LICENSE
License-File: NOTICE
License-File: AUTHORS.md
Requires-Dist: falcon ==3.1.1
Requires-Dist: falcon-cors
Requires-Dist: greenlet ==2.0.1
Requires-Dist: gevent ==22.10.2
Requires-Dist: asn1crypto ==1.0.0
Requires-Dist: ujson
Requires-Dist: markupsafe ==2.0.1
Requires-Dist: sqlalchemy <2.0.0
Requires-Dist: PyYAML
Requires-Dist: PyMYSQL
Requires-Dist: phonenumbers
Requires-Dist: jinja2 ==3.0.3
Requires-Dist: webassets
Requires-Dist: beaker
Requires-Dist: cryptography ==42.0.5
Requires-Dist: python-ldap
Requires-Dist: pytz
Requires-Dist: irisclient
Requires-Dist: slackclient ==1.3.1
Requires-Dist: icalendar
Requires-Dist: pymsteams
Requires-Dist: idna ==2.10
Provides-Extra: dev
Requires-Dist: pytest ==7.1.2 ; extra == 'dev'
Requires-Dist: pytest-mock ; extra == 'dev'
Requires-Dist: requests ; extra == 'dev'
Requires-Dist: gunicorn ==20.1.0 ; extra == 'dev'
Requires-Dist: flake8 ==6.0.0 ; extra == 'dev'
Requires-Dist: Sphinx ==1.5.6 ; extra == 'dev'
Requires-Dist: sphinxcontrib-httpdomain ; extra == 'dev'
Requires-Dist: sphinx-rtd-theme ; extra == 'dev'
Requires-Dist: sphinx-autobuild ; extra == 'dev'
Provides-Extra: ldap
Requires-Dist: python-ldap ; extra == 'ldap'
Provides-Extra: prometheus
Requires-Dist: prometheus-client ; extra == 'prometheus'
